mfishtoolspy/__init__.py
mfishtoolspy/filtering.py
mfishtoolspy/gene_panel_selection.py
mfishtoolspy/mfishtools_archived.py
mfishtoolspy/plotting.py
mfishtoolspy-0.0.1.dist-info/METADATA
mfishtoolspy-0.0.1.dist-info/WHEEL
mfishtoolspy-0.0.1.dist-info/top_level.txt
mfishtoolspy-0.0.1.dist-info/RECORD
