Metadata-Version: 2.1
Name: mfishtoolspy
Version: 0.0.1
Summary: Tools for mFISH data analysis and gene panel selection
Home-page: https://github.com/AllenNeuralDynamics/mfishtoolspy.git
Author: Jinho Kim
Author-email: jinho.kim@alleninstitute.org
Classifier: Programming Language :: Python :: 3
Classifier: Operating System :: OS Independent
Requires-Python: >=3.7
Requires-Dist: numpy
Requires-Dist: pandas
Requires-Dist: scipy
Requires-Dist: matplotlib
Requires-Dist: dask
